pydicom_seg_rb/__init__.py
pydicom_seg_rb/dicom_utils.py
pydicom_seg_rb/reader.py
pydicom_seg_rb/reader_utils.py
pydicom_seg_rb/schemas/common-schema.json
pydicom_seg_rb/schemas/seg-schema.json
pydicom_seg_rb/segmentation_dataset.py
pydicom_seg_rb/template.py
pydicom_seg_rb/typing.py
pydicom_seg_rb/writer.py
pydicom_seg_rb/writer_utils.py
pydicom_seg_rb-1.0.0.dist-info/LICENSE
pydicom_seg_rb-1.0.0.dist-info/METADATA
pydicom_seg_rb-1.0.0.dist-info/WHEEL
pydicom_seg_rb-1.0.0.dist-info/RECORD
