Metadata-Version: 2.1
Name: pydicom-seg-rb
Version: 1.0.0
Summary: Python package for DICOM-SEG medical segmentation file reading and writing
Home-page: https://github.com/pritamrungta/pydicom-seg-rb
License: MIT
Author: Pritam Rungta
Author-email: 59230352+pritamrungta@users.noreply.github.com
Requires-Python: >=3.9
Classifier: License :: OSI Approved :: MIT License
Classifier: Programming Language :: Python :: 3
Classifier: Programming Language :: Python :: 3.9
Classifier: Programming Language :: Python :: 3.10
Classifier: Programming Language :: Python :: 3.11
Classifier: Programming Language :: Python :: 3.12
Requires-Dist: SimpleITK (>=1.2.5)
Requires-Dist: jsonschema (>=3.2.0)
Requires-Dist: numpy (>=2)
Requires-Dist: pydicom (>=1.4.2)
